datumaro/__init__.py
datumaro/__main__.py
datumaro/version.py
datumaro/cli/__init__.py
datumaro/cli/__main__.py
datumaro/cli/commands/__init__.py
datumaro/cli/commands/add.py
datumaro/cli/commands/convert.py
datumaro/cli/commands/create.py
datumaro/cli/commands/diff.py
datumaro/cli/commands/ediff.py
datumaro/cli/commands/explain.py
datumaro/cli/commands/export.py
datumaro/cli/commands/filter.py
datumaro/cli/commands/import_.py
datumaro/cli/commands/info.py
datumaro/cli/commands/merge.py
datumaro/cli/commands/remove.py
datumaro/cli/commands/stats.py
datumaro/cli/commands/transform.py
datumaro/cli/commands/validate.py
datumaro/cli/contexts/__init__.py
datumaro/cli/contexts/model.py
datumaro/cli/contexts/source.py
datumaro/cli/contexts/project/__init__.py
datumaro/cli/contexts/project/diff.py
datumaro/cli/util/__init__.py
datumaro/cli/util/project.py
datumaro/components/__init__.py
datumaro/components/cli_plugin.py
datumaro/components/config.py
datumaro/components/config_model.py
datumaro/components/converter.py
datumaro/components/dataset.py
datumaro/components/dataset_filter.py
datumaro/components/environment.py
datumaro/components/errors.py
datumaro/components/extractor.py
datumaro/components/launcher.py
datumaro/components/operations.py
datumaro/components/project.py
datumaro/components/validator.py
datumaro/components/algorithms/__init__.py
datumaro/components/algorithms/rise.py
datumaro/plugins/__init__.py
datumaro/plugins/camvid_format.py
datumaro/plugins/cifar_format.py
datumaro/plugins/cityscapes_format.py
datumaro/plugins/image_dir_format.py
datumaro/plugins/image_zip_format.py
datumaro/plugins/imagenet_format.py
datumaro/plugins/imagenet_txt_format.py
datumaro/plugins/labelme_format.py
datumaro/plugins/lfw_format.py
datumaro/plugins/market1501_format.py
datumaro/plugins/mnist_csv_format.py
datumaro/plugins/mnist_format.py
datumaro/plugins/mot_format.py
datumaro/plugins/mots_format.py
datumaro/plugins/ndr.py
datumaro/plugins/open_images_format.py
posemaro-1.1.15.dist-info/LICENSE
posemaro-1.1.15.dist-info/METADATA
posemaro-1.1.15.dist-info/WHEEL
posemaro-1.1.15.dist-info/entry_points.txt
posemaro-1.1.15.dist-info/top_level.txt
posemaro-1.1.15.dist-info/RECORD
