Metadata-Version: 2.1
Name: posemaro
Version: 1.1.15
Summary: Dataset Management Framework (Posemaro)
Home-page: https://github.com/certiware/datumaro
Author: certiware
Author-email: certiware.study@gmail.com
License: UNKNOWN
Platform: UNKNOWN
Classifier: Programming Language :: Python :: 3
Classifier: License :: OSI Approved :: MIT License
Classifier: Operating System :: OS Independent
Requires-Python: >=3.6
Requires-Dist: GitPython (>=3.0.8)
Requires-Dist: Pillow (>=6.1.0)
Requires-Dist: PyYAML (>=5.3.1)
Requires-Dist: attrs (>=19.3.0)
Requires-Dist: defusedxml (>=0.6.0)
Requires-Dist: lxml (>=4.4.1)
Requires-Dist: matplotlib (>=3.3.1)
Requires-Dist: numpy (>=1.17.3)
Requires-Dist: opencv-python
Requires-Dist: scikit-image (>=0.15.0)
Requires-Dist: tensorboardX (!=2.3,>=1.8)
Requires-Dist: pycocotools (!=2.0.2,>=2.0.0) ; platform_system != "Windows"
Requires-Dist: pycocotools-windows ; platform_system == "Windows"
Provides-Extra: tf
Requires-Dist: tensorflow ; extra == 'tf'
Provides-Extra: tf-gpu
Requires-Dist: tensorflow-gpu ; extra == 'tf-gpu'
